flask_supporter/__init__.py
flask_supporter/rest_api/__init__.py
flask_supporter/rest_api/rest_api.py
flask_supporter-0.0.16.dist-info/METADATA
flask_supporter-0.0.16.dist-info/WHEEL
flask_supporter-0.0.16.dist-info/top_level.txt
flask_supporter-0.0.16.dist-info/RECORD
