Metadata-Version: 2.1
Name: flask-supporter
Version: 0.0.16
Summary: Flask supporter
Home-page: https://github.com/automatethem/flask-supporter
Author: Sang Ki Kwon
Author-email: automatethem@gmail.com
License: MIT
Platform: UNKNOWN
Requires-Dist: flask
Requires-Dist: flask-ngrok
Requires-Dist: pyngrok
